{"availabilities":null,"data":[{"isInCashAndCarryRange":true,"isInHomeDeliveryRange":true,"availableStocks":[{"type":"CASHCARRY","quantity":34,"updateDateTime":"2024-05-08T15:02:28.537Z","probabilities":[{"type":"THIS_DAY","updateDateTime":"2024-05-08T15:02:28.537Z","communication":{"colour":{"rgbDec":"10,138,0","rgbHex":"#0A8A00","token":"colour-positive"},"messageType":"HIGH_IN_STOCK"}}]}],"classUnitKey":{"classUnitCode":"085","classUnitType":"STO"},"itemKey":{"itemNo":"70445673","itemType":"ART"}},{"isInCashAndCarryRange":true,"isInHomeDeliveryRange":true,"availableStocks":[{"type":"CASHCARRY","quantity":27,"updateDateTime":"2024-05-06T22:39:36.675Z","probabilities":[{"type":"THIS_DAY","updateDateTime":"2024-05-06T22:39:36.675Z","communication":{"colour":{"rgbDec":"10,138,0","rgbHex":"#0A8A00","token":"colour-positive"},"messageType":"HIGH_IN_STOCK"}}]}],"classUnitKey":{"classUnitCode":"090","classUnitType":"STO"},"itemKey":{"itemNo":"70445673","itemType":"ART"}},{"isInCashAndCarryRange":true,"isInHomeDeliveryRange":true,"availableStocks":[{"type":"CASHCARRY","quantity":40,"updateDateTime":"2024-05-04T18:02:31.246Z","probabilities":[{"type":"THIS_DAY","updateDateTime":"2024-05-04T18:02:31.246Z","communication":{"colour":{"rgbDec":"10,138,0","rgbHex":"#0A8A00","token":"colour-positive"},"messageType":"HIGH_IN_STOCK"}}]}],"classUnitKey":{"classUnitCode":"155","classUnitType":"STO"},"itemKey":{"itemNo":"70445673","itemType":"ART"}},{"isInCashAndCarryRange":true,"isInHomeDeliveryRange":true,"availableStocks":[{"type":"CASHCARRY","quantity":23,"updateDateTime":"2024-05-08T16:00:54.618Z","probabilities":[{"type":"THIS_DAY","updateDateTime":"2024-05-08T16:00:54.618Z","communication":{"colour":{"rgbDec":"10,138,0","rgbHex":"#0A8A00","token":"colour-positive"},"messageType":"HIGH_IN_STOCK"}}]}],"classUnitKey":{"classUnitCode":"273","classUnitType":"STO"},"itemKey":{"itemNo":"70445673","itemType":"ART"}},{"isInCashAndCarryRange":true,"isInHomeDeliveryRange":true,"availableStocks":[{"type":"CASHCARRY","quantity":42,"updateDateTime":"2024-05-08T09:03:44.564Z","probabilities":[{"type":"THIS_DAY","updateDateTime":"2024-05-08T09:03:44.564Z","communication":{"colour":{"rgbDec":"10,138,0","rgbHex":"#0A8A00","token":"colour-positive"},"messageType":"HIGH_IN_STOCK"}}]}],"classUnitKey":{"classUnitCode":"386","classUnitType":"STO"},"itemKey":{"itemNo":"70445673","itemType":"ART"}},{"isInCashAndCarryRange":true,"isInHomeDeliveryRange":true,"availableStocks":[{"type":"CASHCARRY","quantity":51,"updateDateTime":"2024-05-08T12:53:01.887Z","probabilities":[{"type":"THIS_DAY","updateDateTime":"2024-05-08T12:53:01.887Z","communication":{"colour":{"rgbDec":"10,138,0","rgbHex":"#0A8A00","token":"colour-positive"},"messageType":"HIGH_IN_STOCK"}}]}],"classUnitKey":{"classUnitCode":"387","classUnitType":"STO"},"itemKey":{"itemNo":"70445673","itemType":"ART"}},{"isInCashAndCarryRange":true,"isInHomeDeliveryRange":true,"availableStocks":[{"type":"CASHCARRY","quantity":29,"updateDateTime":"2024-05-08T14:41:43.582Z","probabilities":[{"type":"THIS_DAY","updateDateTime":"2024-05-08T14:41:43.582Z","communication":{"colour":{"rgbDec":"10,138,0","rgbHex":"#0A8A00","token":"colour-positive"},"messageType":"HIGH_IN_STOCK"}}]}],"classUnitKey":{"classUnitCode":"388","classUnitType":"STO"},"itemKey":{"itemNo":"70445673","itemType":"ART"}},{"isInCashAndCarryRange":true,"isInHomeDeliveryRange":true,"availableStocks":[{"type":"CASHCARRY","quantity":18,"updateDateTime":"2024-05-08T16:47:03.792Z","probabilities":[{"type":"THIS_DAY","updateDateTime":"2024-05-08T16:47:03.792Z","communication":{"colour":{"rgbDec":"10,138,0","rgbHex":"#0A8A00","token":"colour-positive"},"messageType":"HIGH_IN_STOCK"}}]}],"classUnitKey":{"classUnitCode":"587","classUnitType":"STO"},"itemKey":{"itemNo":"70445673","itemType":"ART"}},{"isInCashAndCarryRange":null,"isInHomeDeliveryRange":true,"classUnitKey":{"classUnitCode":"AT","classUnitType":"RU"},"itemKey":{"itemNo":"70445673","itemType":"ART"}}],"timestamp":"2024-05-08T17:16:43.438Z","traceId":"17374058718863894896"}
