{"availabilities":null,"data":[{"isInCashAndCarryRange":true,"isInHomeDeliveryRange":true,"availableStocks":[{"type":"CASHCARRY","quantity":139,"updateDateTime":"2024-05-08T15:02:28.550Z","probabilities":[{"type":"THIS_DAY","updateDateTime":"2024-05-08T15:02:28.550Z","communication":{"colour":{"rgbDec":"10,138,0","rgbHex":"#0A8A00","token":"colour-positive"},"messageType":"HIGH_IN_STOCK"}}]}],"classUnitKey":{"classUnitCode":"085","classUnitType":"STO"},"itemKey":{"itemNo":"50460527","itemType":"ART"}},{"isInCashAndCarryRange":true,"isInHomeDeliveryRange":true,"availableStocks":[{"type":"CASHCARRY","quantity":68,"updateDateTime":"2024-05-08T14:35:36.350Z","probabilities":[{"type":"THIS_DAY","updateDateTime":"2024-05-08T14:35:36.350Z","communication":{"colour":{"rgbDec":"10,138,0","rgbHex":"#0A8A00","token":"colour-positive"},"messageType":"HIGH_IN_STOCK"}}]}],"classUnitKey":{"classUnitCode":"090","classUnitType":"STO"},"itemKey":{"itemNo":"50460527","itemType":"ART"}},{"isInCashAndCarryRange":true,"isInHomeDeliveryRange":true,"availableStocks":[{"type":"CASHCARRY","quantity":72,"updateDateTime":"2024-05-08T14:22:30.663Z","probabilities":[{"type":"THIS_DAY","updateDateTime":"2024-05-08T14:22:30.663Z","communication":{"colour":{"rgbDec":"10,138,0","rgbHex":"#0A8A00","token":"colour-positive"},"messageType":"HIGH_IN_STOCK"}}]}],"classUnitKey":{"classUnitCode":"155","classUnitType":"STO"},"itemKey":{"itemNo":"50460527","itemType":"ART"}},{"isInCashAndCarryRange":true,"isInHomeDeliveryRange":true,"availableStocks":[{"type":"CASHCARRY","quantity":119,"updateDateTime":"2024-05-08T16:56:54.929Z","probabilities":[{"type":"THIS_DAY","updateDateTime":"2024-05-08T16:56:54.929Z","communication":{"colour":{"rgbDec":"10,138,0","rgbHex":"#0A8A00","token":"colour-positive"},"messageType":"HIGH_IN_STOCK"}}]}],"classUnitKey":{"classUnitCode":"273","classUnitType":"STO"},"itemKey":{"itemNo":"50460527","itemType":"ART"}},{"isInCashAndCarryRange":true,"isInHomeDeliveryRange":true,"availableStocks":[{"type":"CASHCARRY","quantity":263,"updateDateTime":"2024-05-08T16:51:44.505Z","probabilities":[{"type":"THIS_DAY","updateDateTime":"2024-05-08T16:51:44.505Z","communication":{"colour":{"rgbDec":"10,138,0","rgbHex":"#0A8A00","token":"colour-positive"},"messageType":"HIGH_IN_STOCK"}}]}],"classUnitKey":{"classUnitCode":"386","classUnitType":"STO"},"itemKey":{"itemNo":"50460527","itemType":"ART"}},{"isInCashAndCarryRange":true,"isInHomeDeliveryRange":true,"availableStocks":[{"type":"CASHCARRY","quantity":125,"updateDateTime":"2024-05-08T15:41:01.931Z","probabilities":[{"type":"THIS_DAY","updateDateTime":"2024-05-08T15:41:01.931Z","communication":{"colour":{"rgbDec":"10,138,0","rgbHex":"#0A8A00","token":"colour-positive"},"messageType":"HIGH_IN_STOCK"}}]}],"classUnitKey":{"classUnitCode":"387","classUnitType":"STO"},"itemKey":{"itemNo":"50460527","itemType":"ART"}},{"isInCashAndCarryRange":true,"isInHomeDeliveryRange":true,"availableStocks":[{"type":"CASHCARRY","quantity":111,"updateDateTime":"2024-05-08T14:53:43.497Z","probabilities":[{"type":"THIS_DAY","updateDateTime":"2024-05-08T14:53:43.497Z","communication":{"colour":{"rgbDec":"10,138,0","rgbHex":"#0A8A00","token":"colour-positive"},"messageType":"HIGH_IN_STOCK"}}]}],"classUnitKey":{"classUnitCode":"388","classUnitType":"STO"},"itemKey":{"itemNo":"50460527","itemType":"ART"}},{"isInCashAndCarryRange":true,"isInHomeDeliveryRange":true,"availableStocks":[{"type":"CASHCARRY","quantity":96,"updateDateTime":"2024-05-08T14:48:22.315Z","probabilities":[{"type":"THIS_DAY","updateDateTime":"2024-05-08T14:48:22.315Z","communication":{"colour":{"rgbDec":"10,138,0","rgbHex":"#0A8A00","token":"colour-positive"},"messageType":"HIGH_IN_STOCK"}}]}],"classUnitKey":{"classUnitCode":"587","classUnitType":"STO"},"itemKey":{"itemNo":"50460527","itemType":"ART"}},{"isInCashAndCarryRange":null,"isInHomeDeliveryRange":true,"classUnitKey":{"classUnitCode":"AT","classUnitType":"RU"},"itemKey":{"itemNo":"50460527","itemType":"ART"}}],"timestamp":"2024-05-08T17:12:30.850Z","traceId":"14502663580809372579"}
