{"availabilities":null,"data":[{"isInCashAndCarryRange":true,"isInHomeDeliveryRange":true,"availableStocks":[{"type":"CASHCARRY","quantity":14,"updateDateTime":"2024-05-08T13:22:29.582Z","probabilities":[{"type":"THIS_DAY","updateDateTime":"2024-05-08T13:22:29.582Z","communication":{"colour":{"rgbDec":"10,138,0","rgbHex":"#0A8A00","token":"colour-positive"},"messageType":"HIGH_IN_STOCK"}}]}],"classUnitKey":{"classUnitCode":"085","classUnitType":"STO"},"itemKey":{"itemNo":"70567725","itemType":"ART"}},{"isInCashAndCarryRange":true,"isInHomeDeliveryRange":true,"availableStocks":[{"type":"CASHCARRY","quantity":29,"updateDateTime":"2024-05-08T08:55:36.549Z","probabilities":[{"type":"THIS_DAY","updateDateTime":"2024-05-08T08:55:36.549Z","communication":{"colour":{"rgbDec":"10,138,0","rgbHex":"#0A8A00","token":"colour-positive"},"messageType":"HIGH_IN_STOCK"}}]}],"classUnitKey":{"classUnitCode":"090","classUnitType":"STO"},"itemKey":{"itemNo":"70567725","itemType":"ART"}},{"isInCashAndCarryRange":true,"isInHomeDeliveryRange":true,"availableStocks":[{"type":"CASHCARRY","quantity":58,"updateDateTime":"2024-05-04T18:02:31.296Z","probabilities":[{"type":"THIS_DAY","updateDateTime":"2024-05-04T18:02:31.296Z","communication":{"colour":{"rgbDec":"10,138,0","rgbHex":"#0A8A00","token":"colour-positive"},"messageType":"HIGH_IN_STOCK"}}]}],"classUnitKey":{"classUnitCode":"155","classUnitType":"STO"},"itemKey":{"itemNo":"70567725","itemType":"ART"}},{"isInCashAndCarryRange":true,"isInHomeDeliveryRange":true,"availableStocks":[{"type":"CASHCARRY","quantity":75,"updateDateTime":"2024-05-04T17:48:55.314Z","probabilities":[{"type":"THIS_DAY","updateDateTime":"2024-05-04T17:48:55.314Z","communication":{"colour":{"rgbDec":"10,138,0","rgbHex":"#0A8A00","token":"colour-positive"},"messageType":"HIGH_IN_STOCK"}}]}],"classUnitKey":{"classUnitCode":"273","classUnitType":"STO"},"itemKey":{"itemNo":"70567725","itemType":"ART"}},{"isInCashAndCarryRange":true,"isInHomeDeliveryRange":true,"availableStocks":[{"type":"CASHCARRY","quantity":70,"updateDateTime":"2024-05-03T23:19:45.791Z","probabilities":[{"type":"THIS_DAY","updateDateTime":"2024-05-03T23:19:45.791Z","communication":{"colour":{"rgbDec":"10,138,0","rgbHex":"#0A8A00","token":"colour-positive"},"messageType":"HIGH_IN_STOCK"}}]}],"classUnitKey":{"classUnitCode":"386","classUnitType":"STO"},"itemKey":{"itemNo":"70567725","itemType":"ART"}},{"isInCashAndCarryRange":true,"isInHomeDeliveryRange":true,"availableStocks":[{"type":"CASHCARRY","quantity":112,"updateDateTime":"2024-05-06T23:25:03.453Z","probabilities":[{"type":"THIS_DAY","updateDateTime":"2024-05-06T23:25:03.453Z","communication":{"colour":{"rgbDec":"10,138,0","rgbHex":"#0A8A00","token":"colour-positive"},"messageType":"HIGH_IN_STOCK"}}]}],"classUnitKey":{"classUnitCode":"387","classUnitType":"STO"},"itemKey":{"itemNo":"70567725","itemType":"ART"}},{"isInCashAndCarryRange":true,"isInHomeDeliveryRange":true,"availableStocks":[{"type":"CASHCARRY","quantity":59,"updateDateTime":"2024-05-06T23:17:43.844Z","probabilities":[{"type":"THIS_DAY","updateDateTime":"2024-05-06T23:17:43.844Z","communication":{"colour":{"rgbDec":"10,138,0","rgbHex":"#0A8A00","token":"colour-positive"},"messageType":"HIGH_IN_STOCK"}}]}],"classUnitKey":{"classUnitCode":"388","classUnitType":"STO"},"itemKey":{"itemNo":"70567725","itemType":"ART"}},{"isInCashAndCarryRange":true,"isInHomeDeliveryRange":true,"availableStocks":[{"type":"CASHCARRY","quantity":26,"updateDateTime":"2024-05-06T19:07:05.229Z","probabilities":[{"type":"THIS_DAY","updateDateTime":"2024-05-06T19:07:05.229Z","communication":{"colour":{"rgbDec":"10,138,0","rgbHex":"#0A8A00","token":"colour-positive"},"messageType":"HIGH_IN_STOCK"}}]}],"classUnitKey":{"classUnitCode":"587","classUnitType":"STO"},"itemKey":{"itemNo":"70567725","itemType":"ART"}},{"isInCashAndCarryRange":null,"isInHomeDeliveryRange":true,"classUnitKey":{"classUnitCode":"AT","classUnitType":"RU"},"itemKey":{"itemNo":"70567725","itemType":"ART"}}],"timestamp":"2024-05-08T17:23:13.257Z","traceId":"5391019613026414339"}
