{"availabilities":null,"data":[{"isInCashAndCarryRange":true,"isInHomeDeliveryRange":true,"availableStocks":[{"type":"CASHCARRY","quantity":79,"updateDateTime":"2024-05-08T16:30:28.260Z","probabilities":[{"type":"THIS_DAY","updateDateTime":"2024-05-08T16:30:28.260Z","communication":{"colour":{"rgbDec":"10,138,0","rgbHex":"#0A8A00","token":"colour-positive"},"messageType":"HIGH_IN_STOCK"}}]}],"classUnitKey":{"classUnitCode":"085","classUnitType":"STO"},"itemKey":{"itemNo":"80507991","itemType":"ART"}},{"isInCashAndCarryRange":true,"isInHomeDeliveryRange":true,"availableStocks":[{"type":"CASHCARRY","quantity":122,"updateDateTime":"2024-05-08T15:07:36.344Z","probabilities":[{"type":"THIS_DAY","updateDateTime":"2024-05-08T15:07:36.344Z","communication":{"colour":{"rgbDec":"10,138,0","rgbHex":"#0A8A00","token":"colour-positive"},"messageType":"HIGH_IN_STOCK"}}]}],"classUnitKey":{"classUnitCode":"090","classUnitType":"STO"},"itemKey":{"itemNo":"80507991","itemType":"ART"}},{"isInCashAndCarryRange":true,"isInHomeDeliveryRange":true,"availableStocks":[{"type":"CASHCARRY","quantity":155,"updateDateTime":"2024-05-08T12:06:30.857Z","probabilities":[{"type":"THIS_DAY","updateDateTime":"2024-05-08T12:06:30.857Z","communication":{"colour":{"rgbDec":"10,138,0","rgbHex":"#0A8A00","token":"colour-positive"},"messageType":"HIGH_IN_STOCK"}}]}],"classUnitKey":{"classUnitCode":"155","classUnitType":"STO"},"itemKey":{"itemNo":"80507991","itemType":"ART"}},{"isInCashAndCarryRange":true,"isInHomeDeliveryRange":true,"availableStocks":[{"type":"CASHCARRY","quantity":136,"updateDateTime":"2024-05-08T15:16:54.855Z","probabilities":[{"type":"THIS_DAY","updateDateTime":"2024-05-08T15:16:54.855Z","communication":{"colour":{"rgbDec":"10,138,0","rgbHex":"#0A8A00","token":"colour-positive"},"messageType":"HIGH_IN_STOCK"}}]}],"classUnitKey":{"classUnitCode":"273","classUnitType":"STO"},"itemKey":{"itemNo":"80507991","itemType":"ART"}},{"isInCashAndCarryRange":true,"isInHomeDeliveryRange":true,"availableStocks":[{"type":"CASHCARRY","quantity":112,"updateDateTime":"2024-05-08T13:31:44.765Z","probabilities":[{"type":"THIS_DAY","updateDateTime":"2024-05-08T13:31:44.765Z","communication":{"colour":{"rgbDec":"10,138,0","rgbHex":"#0A8A00","token":"colour-positive"},"messageType":"HIGH_IN_STOCK"}}]}],"classUnitKey":{"classUnitCode":"386","classUnitType":"STO"},"itemKey":{"itemNo":"80507991","itemType":"ART"}},{"isInCashAndCarryRange":true,"isInHomeDeliveryRange":true,"availableStocks":[{"type":"CASHCARRY","quantity":36,"updateDateTime":"2024-05-08T11:05:03.628Z","probabilities":[{"type":"THIS_DAY","updateDateTime":"2024-05-08T11:05:03.628Z","communication":{"colour":{"rgbDec":"10,138,0","rgbHex":"#0A8A00","token":"colour-positive"},"messageType":"HIGH_IN_STOCK"}}]}],"classUnitKey":{"classUnitCode":"387","classUnitType":"STO"},"itemKey":{"itemNo":"80507991","itemType":"ART"}},{"isInCashAndCarryRange":true,"isInHomeDeliveryRange":true,"availableStocks":[{"type":"CASHCARRY","quantity":205,"updateDateTime":"2024-05-08T17:09:43.871Z","probabilities":[{"type":"THIS_DAY","updateDateTime":"2024-05-08T17:09:43.871Z","communication":{"colour":{"rgbDec":"10,138,0","rgbHex":"#0A8A00","token":"colour-positive"},"messageType":"HIGH_IN_STOCK"}}]}],"classUnitKey":{"classUnitCode":"388","classUnitType":"STO"},"itemKey":{"itemNo":"80507991","itemType":"ART"}},{"isInCashAndCarryRange":false,"isInHomeDeliveryRange":true,"classUnitKey":{"classUnitCode":"587","classUnitType":"STO"},"itemKey":{"itemNo":"80507991","itemType":"ART"}},{"isInCashAndCarryRange":null,"isInHomeDeliveryRange":true,"classUnitKey":{"classUnitCode":"AT","classUnitType":"RU"},"itemKey":{"itemNo":"80507991","itemType":"ART"}}],"timestamp":"2024-05-08T17:14:15.486Z","traceId":"10344023338723448886"}
